Metadata-Version: 2.1
Name: minuteinbox-py
Version: 0.4
Summary: Create temporary E-Mails & receive E-Mails with MinuteInbox through python
Home-page: https://github.com/Avnsx/MinuteInbox-Temporary-E-Mail
Author: Mika C
Author-email: AvnDev@protonmail.com
License: MIT
Keywords: email,minuteinbox,temporary,disposable,spam,mail,10 minute,python email,
Platform: UNKNOWN
Classifier: Development Status :: 5 - Production/Stable
Classifier: Operating System :: Microsoft :: Windows :: Windows 10
Classifier: License :: OSI Approved :: MIT License
Classifier: Programming Language :: Python :: 3
License-File: LICENSE.txt
